SeismicUtils/Records.py
SeismicUtils/Spectrum.py
SeismicUtils/__init__.py
SeismicUtils/calculus.py
seismic_utils-1.4.dist-info/METADATA
seismic_utils-1.4.dist-info/WHEEL
seismic_utils-1.4.dist-info/top_level.txt
seismic_utils-1.4.dist-info/RECORD
